openpiv/PIV_3D_plotting.py
openpiv/__init__.py
openpiv/data/test1/exp1_001_a.bmp
openpiv/data/test1/exp1_001_b.bmp
openpiv/data/test1/test_data.vec
openpiv/data/test2/2image_00.tif
openpiv/data/test2/2image_01.tif
openpiv/data/test2/2image_10.tif
openpiv/data/test2/2image_11.tif
openpiv/data/test2/2image_20.tif
openpiv/data/test2/2image_21.tif
openpiv/data/test2/2image_30.tif
openpiv/data/test2/2image_31.tif
openpiv/data/test2/2image_40.tif
openpiv/data/test2/2image_41.tif
openpiv/data/test2/2image_50.tif
openpiv/data/test2/2image_51.tif
openpiv/data/test3/pair_4_frame_0.jpg
openpiv/data/test3/pair_4_frame_1.jpg
openpiv/data/test4/Camera1-0101.tif
openpiv/data/test4/Camera1-0102.tif
openpiv/data/test5/Pattern_10_A.tif
openpiv/data/test5/Pattern_10_B.tif
openpiv/data/test5/Pattern_1_A.tif
openpiv/data/test5/Pattern_1_B.tif
openpiv/data/test5/Pattern_2_A.tif
openpiv/data/test5/Pattern_2_B.tif
openpiv/data/test5/Pattern_3_A.tif
openpiv/data/test5/Pattern_3_B.tif
openpiv/data/test5/Pattern_4_A.tif
openpiv/data/test5/Pattern_4_B.tif
openpiv/data/test5/Pattern_5_A.tif
openpiv/data/test5/Pattern_5_B.tif
openpiv/data/test5/Pattern_6_A.tif
openpiv/data/test5/Pattern_6_B.tif
openpiv/data/test5/Pattern_7_A.tif
openpiv/data/test5/Pattern_7_B.tif
openpiv/data/test5/Pattern_8_A.tif
openpiv/data/test5/Pattern_8_B.tif
openpiv/data/test5/Pattern_9_A.tif
openpiv/data/test5/Pattern_9_B.tif
openpiv/data/test6/Pattern_0001_A.tif
openpiv/data/test6/Pattern_0002_A.tif
openpiv/data/test6/Pattern_0003_A.tif
openpiv/data/test6/Pattern_0004_A.tif
openpiv/data/test6/Pattern_0005_A.tif
openpiv/data/test6/Pattern_1001_B.tif
openpiv/data/test6/Pattern_1002_B.tif
openpiv/data/test6/Pattern_1003_B.tif
openpiv/data/test6/Pattern_1004_B.tif
openpiv/data/test6/Pattern_1005_B.tif
openpiv/docs/Makefile
openpiv/docs/OpenPIV.pdf
openpiv/docs/OpenPIV_advanced_processing_parameters.pdf
openpiv/docs/conf.py
openpiv/docs/images/B005_1.tif
openpiv/docs/images/B005_2.tif
openpiv/docs/images/image1.png
openpiv-0.25.3.dist-info/LICENSE.txt
openpiv-0.25.3.dist-info/METADATA
openpiv-0.25.3.dist-info/WHEEL
openpiv-0.25.3.dist-info/entry_points.txt
openpiv-0.25.3.dist-info/RECORD
