Metadata-Version: 2.1
Name: OpenPIV
Version: 0.25.3
Summary: OpenPIV consists in a Python and Cython modules for scripting and executing the analysis of a set of PIV image pairs. In addition, a Qt and Tk graphical user interfaces are in development, to ease the use for those users who don't have python skills.
License: GPLv3
Author: Alex Liberzon
Requires-Python: >=3.10
Classifier: Development Status :: 4 - Beta
Classifier: Intended Audience :: Science/Research
Classifier: License :: OSI Approved :: GNU General Public License v3 (GPLv3)
Classifier: License :: Other/Proprietary License
Classifier: Natural Language :: English
Classifier: Operating System :: MacOS :: MacOS X
Classifier: Operating System :: Microsoft :: Windows
Classifier: Operating System :: OS Independent
Classifier: Operating System :: POSIX
Classifier: Programming Language :: Python :: 3
Classifier: Programming Language :: Python :: 3.10
Classifier: Programming Language :: Python :: 3.11
Classifier: Programming Language :: Python :: 3.12
Classifier: Programming Language :: Python :: 3.7
Classifier: Programming Language :: Python :: 3.8
Classifier: Programming Language :: Python :: 3.9
Classifier: Topic :: Scientific/Engineering
Requires-Dist: imageio (>=2.22.4,<3.0.0)
Requires-Dist: importlib_resources (==5.12.0)
Requires-Dist: matplotlib (>=3,<4)
Requires-Dist: natsort (>=8.4.0,<9.0.0)
Requires-Dist: numpy (>=1.21.6,<2.0.0)
Requires-Dist: scikit-image (>=0.23)
Requires-Dist: scipy (>=1.7.3,<2.0.0)
Requires-Dist: tqdm (>=4.66.1,<5.0.0)
Project-URL: Documentation, http://openpiv.readthedocs.org
Project-URL: Repository, https://pypi.python.org/pypi/OpenPIV
